{"file:///C:/elements/Documents%20-%20sata/files-1018/AZTS":{"assets/images/hashes.json":"/64f6u7hMIfT8YbWYXPb2w==","assets/images/news-logo.png":"nd3eRezwgFTbIBA7v/cXrw==","assets/images/01.jpg":"Qcwozc7QLOMX9Oz/6UaFkw==","assets/images/3-3111-aigo-rue-hd-scaled-1800x800-c-bottom-center-970x431.jpg":"3CCQg+KpvzIrqLZ5LTabQw==","assets/images/7-photo-ext-7316-030-277j68-970x445.jpg":"+/bk4nh9WJ60qXJXqYu92w==","assets/images/photo-ext-7141-030-293j69.jpeg":"FMp4kXyWfUgQhCsFxxSHNg==","assets/images/orpi-tout-lete.jpg":"7CpCv2FOJk4paQmdZF9hjw==","assets/images/background4.jpg":"RZlqKUhsQY1aTjl145kzIw==","assets/images/9.jpg":"nYay/rmjFPncDhgWrI+nJA==","assets/images/bondy5-1.jpg":"YRsCkED0oPw2PE1sSnRoCg==","assets/images/asnieres.jpg":"LY7znKJANl7duO4eRLz6jQ==","assets/images/melun.jpg":"dMihaBLz/bVwKrGQoRoqHw==","assets/images/meaux.jpg":"W7MO5JSzOE+xNrYrUgtuSA==","assets/images/romain.jpg":"R08S4RUyrsR8OYF+fGssVg==","assets/images/elanc.jpg":"vRYIBFvVUlP3ctrbCUS4UQ==","assets/images/cap-west.jpeg":"NJAgagNGhQm5nUugBUEQDQ==","assets/images/vsg.jpeg":"Ir3W3AY0Y+wsVx33LwFPaw==","assets/images/livry.jpeg":"+0LCralHF0YX5ki2OtFQWg==","assets/images/morangis.jpeg":"7hUs32isB97j7Tp35Ls4sw==","assets/images/sq2.jpg":"sjHxoafI/vZxU1GIyjkYng==","assets/images/sq1.jpg":"j9AT/IEcpiIRQHn2kPxJcw==","assets/images/ha.png":"iFod5Rb35et1JhDNuC9UxA==","assets/images/jc.png":"PGSkdh0wu36OAzc/0LWHhg==","assets/images/be7cb0e7-48b5-44fb-a56e-83d737cc3dae.jpeg":"0unIy8qXYTOijA4wpUpGcQ==","assets/images/nl.png":"lq5Um0z131fxHLcZE58l0Q==","assets/images/bf7aeaaf-84ff-411f-b474-c44e6ca37ca1.jpeg":"qs7/RioAG9yhORgs1g9xFA==","assets/images/9277064h.jpeg":"8O5M54sBYV39BhEIhPKYUQ==","assets/images/9138778a.jpeg":"0+RU/WkltitGaDpUSDc0qQ==","assets/images/9272296a.jpeg":"6yElUPORSl+77djHmDRtGA==","assets/images/az.jpg":"irm22wBrjmhpkrB+YUKtWA==","assets/images/az3.jpg":"jeqdKcDNMP9rtd3ehgIBvw==","assets/images/9138778i.jpg":"mi4J0pw/WDuynUHkTdI33Q==","assets/images/az1-1.jpg":"0yrff9SryFS821tb+HEI7Q==","assets/images/07.jpg":"mVePavJ68LSO47ALJfbn4A==","assets/images/photo-ext-7142-030-293j69.jpeg":"1T7RlWNMWk/wnsJRG7/vNw==","assets/web/assets/jquery/jquery.min.js":"3F5/GMjTasHT1HU6h8mNCg==","assets/web/assets/gdpr-plugin/gdpr-styles.css":"Q2M06aDX0w6H1VVhUBSUCg==","assets/bootstrap/css/bootstrap.min.css":"gWrw7d07SCLCdWInx+e37g==","assets/bootstrap/css/bootstrap-grid.min.css":"ZpQEaHtj4rsdGDC9wDZdfg==","assets/bootstrap/css/bootstrap-reboot.min.css":"eMZwSLVvZudwLH9xiGj50w==","assets/bootstrap/js/bootstrap.min.js":"AtIjOT4AwnPv3LGt6PT4sQ==","assets/popper/popper.min.js":"NiE4ESlZe/NNSKniYj4FyQ==","assets/tether/tether.min.css":"YhVaOUjL8Xsb9LQHyQq4Tw==","assets/tether/tether.min.js":"PlC291/0Eo8keLHUT4D9+w==","assets/theme/css/style.css":"TToltBSF6Y4a0NZLoX3hQw==-VITbTf54ezV7Z7I/e4lZVw==","assets/smoothscroll/smooth-scroll.js":"e15+ccLIeWb2A3ZYIotPaw==","assets/chatbutton/floating-wpp.js":"9h0T7LKVutmCFrpeOrvMqw==","assets/chatbutton/floating-wpp.css":"RTKg5FdHkVg2hj2Lmy4Dlg==","assets/chatbutton/script.js":"3wwnCZOzMGYeRyCnTuzDaA==","assets/dropdown/css/style.css":"s+S8lVC62P0BWFtgHpaNFA==","assets/dropdown/js/nav-dropdown.js":"j5pq4WKLRnihd7IVVkQkJg==","assets/dropdown/js/navbar-dropdown.js":"RJXH/341Oa7csvj4pGRDfQ==","assets/touchswipe/jquery.touch-swipe.min.js":"9g/wVGnRdXmW2F9BctT/TQ==","assets/formstyler/jquery.formstyler.css":"ajjp8ztH9eVUk4rdhVGFYg==","assets/formstyler/jquery.formstyler.js":"Xv5CrVBApokt3elzzhEwuQ==","assets/formstyler/jquery.formstyler.min.js":"AZwL++bNUiLJxmlnInDaEQ==","assets/formstyler/jquery.formstyler.theme.css":"nnzXNu6YBQzXtwPVnmSyMQ==","assets/datepicker/jquery.datetimepicker.min.css":"ho+tif2BPmsXNeoVpuhDPg==","assets/datepicker/jquery.datetimepicker.full.js":"TcRSAGiGustgTlkirRSsRg==","assets/playervimeo/vimeo_player.js":"IV5sj41WErhIy+BRgYWT7Q==","assets/parallax/jarallax.min.js":"rX/x1RkUP0ZMvZZrsxrg7A==","assets/web/assets/mobirise-icons/mobirise-icons.css":"t/IrTIzfJvbDUoCV05F+7Q==","assets/web/assets/mobirise-icons/mobirise-icons.eot":"T9iJ+Vffe7n6Gk/+pf9gEw==","assets/web/assets/mobirise-icons/mobirise-icons.svg":"Yp5pSlGdnLgPdQLUa/Yv3w==","assets/web/assets/mobirise-icons/mobirise-icons.ttf":"r0OtN8kuMaYwUc+mlGDUWA==","assets/web/assets/mobirise-icons/mobirise-icons.woff":"3aYYVAIqADvsB1jjxJZ73w==","assets/FontAwesome/css/font-awesome.css":"MUQUl2Kv/7aja2ZwCX6jLw==","assets/FontAwesome/fonts/fontawesome-webfont.eot":"AW+kUDOpQv/srclw8i/kGw==","assets/FontAwesome/fonts/fontawesome-webfont.svg":"kS7GbXVy/4IXSTGTlkcL3g==","assets/FontAwesome/fonts/fontawesome-webfont.ttf":"7OvOOrlbZkCRm2svZrRL+A==","assets/FontAwesome/fonts/fontawesome-webfont.woff":"XgOIrq4WRpdzuM904tYwSw==","assets/FontAwesome/fonts/fontawesome-webfont.woff2":"2CmzIlHkI4BsqciqZAt9zw==","assets/FontAwesome/fonts/FontAwesome.otf":"ZjI216pEdiC2QQMtG3vlfA==","assets/web/assets/mobirise-icons2/mobirise2.css":"+RO7OxVtE1FsD/N7V3/ADw==","assets/web/assets/mobirise-icons2/mobirise2.eot":"B2EjryGRojlTpzr1GHt3LQ==","assets/web/assets/mobirise-icons2/mobirise2.svg":"usCYAy7QdzckfeGReb9wWQ==","assets/web/assets/mobirise-icons2/mobirise2.ttf":"VMdAr7YYQ2ab9KiUyabAGA==","assets/web/assets/mobirise-icons2/mobirise2.woff":"xY3InaTfYGp0nlCuQBMudQ==","assets/socicon/css/styles.css":"yjHs7tV2SewoW36KZ0bi9w==","assets/socicon/fonts/socicon.eot":"MvYQV8XxgngrhGqjN3oHBw==","assets/socicon/fonts/socicon.svg":"U1iRKoyNjKeR+mUJr3QbXg==","assets/socicon/fonts/socicon.ttf":"IyAo3XNB2a/Q0ml3ZraPsQ==","assets/socicon/fonts/socicon.woff":"zQDjXd6bBUQi87pRsBWVqQ==","assets/socicon/fonts/socicon.woff2":"o3w8h99EHOwP99NXAoHpOQ==","assets/formoid.min.js":"PCIvx4TB4BdNTxFrmRNOkQ==","assets/recaptcha.css":"rAr6hicA8NHvvo8fHdDrDQ=="}}